odml/__init__.py
odml/base.py
odml/doc.py
odml/dtypes.py
odml/fileio.py
odml/format.py
odml/info.json
odml/info.py
odml/property.py
odml/section.py
odml/templates.py
odml/terminology.py
odml/util.py
odml/validation.py
odml/rdf/__init__.py
odml/rdf/fuzzy_finder.py
odml/rdf/query_creator.py
odml/resources/odml-ontology.ttl
odml/resources/section_subclasses.yaml
odml/scripts/__init__.py
odml/scripts/odml_convert.py
odml/scripts/odml_to_rdf.py
odml/scripts/odml_view.py
odml/tools/__init__.py
odml/tools/dict_parser.py
odml/tools/doc_inherit.py
odml/tools/dumper.py
odml/tools/odmlparser.py
odml/tools/parser_utils.py
odml/tools/rdf_converter.py
odml/tools/version_converter.py
odml/tools/xmlparser.py
odml/tools/converters/__init__.py
odml/tools/converters/format_converter.py
odml/tools/converters/version_converter.py
odML-1.5.4.dist-info/LICENSE
odML-1.5.4.dist-info/METADATA
odML-1.5.4.dist-info/WHEEL
odML-1.5.4.dist-info/entry_points.txt
odML-1.5.4.dist-info/top_level.txt
odML-1.5.4.dist-info/RECORD
