Metadata-Version: 2.1
Name: odML
Version: 1.5.4
Summary: open metadata Markup Language
Home-page: https://github.com/G-Node/python-odml
Author: Hagen Fritsch, Jan Grewe, Christian Kellner, Achilleas Koutsou, Michael Sonntag, Lyuba Zehl
Author-email: dev@g-node.org
License: BSD
Classifier: Development Status :: 5 - Production/Stable
Classifier: Programming Language :: Python
Classifier: Programming Language :: Python :: 3.7
Classifier: Programming Language :: Python :: 3.8
Classifier: Programming Language :: Python :: 3.9
Classifier: Programming Language :: Python :: 3.10
Classifier: Topic :: Scientific/Engineering
Classifier: Intended Audience :: Science/Research
Classifier: License :: OSI Approved :: BSD License
License-File: LICENSE
Requires-Dist: docopt
Requires-Dist: lxml
Requires-Dist: pyyaml >=5.1
Requires-Dist: rdflib >=6.0.0
